tcp_latency/__init__.py
tcp_latency/tcp_latency.py
tcp_latency-0.0.12.dist-info/LICENSE.md
tcp_latency-0.0.12.dist-info/METADATA
tcp_latency-0.0.12.dist-info/WHEEL
tcp_latency-0.0.12.dist-info/entry_points.txt
tcp_latency-0.0.12.dist-info/top_level.txt
tcp_latency-0.0.12.dist-info/RECORD
