Metadata-Version: 2.1
Name: tcp-latency
Version: 0.0.12
Summary: Measure latency using TCP.
Home-page: https://github.com/dgzlopes/tcp-latency
Author: Daniel Gonzalez Lopes
Author-email: danielgonzalezlopes@gmail.com
License: MIT
Platform: UNKNOWN
Classifier: Development Status :: 3 - Alpha
Classifier: Intended Audience :: Developers
Classifier: Natural Language :: English
Classifier: Programming Language :: Python :: 3.6
Classifier: Programming Language :: Python :: 3.7
Classifier: Programming Language :: Python :: 3.8
Classifier: License :: OSI Approved :: MIT License
Classifier: Topic :: System :: Networking
Requires-Python: >=3.6
